weather_clothing/__init__.py
weather_clothing/clothing_item.py
weather_clothing/comparisons.py
weather_clothing-0.2.0.dist-info/LICENSE
weather_clothing-0.2.0.dist-info/WHEEL
weather_clothing-0.2.0.dist-info/METADATA
weather_clothing-0.2.0.dist-info/RECORD
