Metadata-Version: 2.1
Name: weather_clothing
Version: 0.2.0
Summary: A Package to help decide what outdoor clothing is appropriate based on the forecast.
Author-email: Duncan van Zyl <duncanvanzyl@gmail.com>
Requires-Python: ~=3.9
Classifier: License :: OSI Approved :: MIT License
Project-URL: Home, https://github.com/duncanvanzyl/weather-clothing
